airbyte_cdk/__init__.py
airbyte_cdk/cli/__init__.py
airbyte_cdk/cli/airbyte_cdk/__init__.py
airbyte_cdk/cli/airbyte_cdk/_connector.py
airbyte_cdk/cli/airbyte_cdk/_image.py
airbyte_cdk/cli/airbyte_cdk/_manifest.py
airbyte_cdk/cli/airbyte_cdk/_secrets.py
airbyte_cdk/cli/airbyte_cdk/_version.py
airbyte_cdk/cli/airbyte_cdk/exceptions.py
airbyte_cdk/cli/source_declarative_manifest/README.md
airbyte_cdk/cli/source_declarative_manifest/__init__.py
airbyte_cdk/cli/source_declarative_manifest/_run.py
airbyte_cdk/cli/source_declarative_manifest/spec.json
airbyte_cdk/config_observation.py
airbyte_cdk/connector.py
airbyte_cdk/connector_builder/README.md
airbyte_cdk/connector_builder/__init__.py
airbyte_cdk/connector_builder/connector_builder_handler.py
airbyte_cdk/connector_builder/main.py
airbyte_cdk/connector_builder/models.py
airbyte_cdk/connector_builder/test_reader/__init__.py
airbyte_cdk/connector_builder/test_reader/helpers.py
airbyte_cdk/connector_builder/test_reader/message_grouper.py
airbyte_cdk/connector_builder/test_reader/reader.py
airbyte_cdk/connector_builder/test_reader/types.py
airbyte_cdk/destinations/__init__.py
airbyte_cdk/destinations/destination.py
airbyte_cdk/destinations/vector_db_based/README.md
airbyte_cdk/destinations/vector_db_based/__init__.py
airbyte_cdk/destinations/vector_db_based/config.py
airbyte_cdk/destinations/vector_db_based/document_processor.py
airbyte_cdk/destinations/vector_db_based/embedder.py
airbyte_cdk/destinations/vector_db_based/indexer.py
airbyte_cdk/destinations/vector_db_based/test_utils.py
airbyte_cdk/destinations/vector_db_based/utils.py
airbyte_cdk/destinations/vector_db_based/writer.py
airbyte_cdk/entrypoint.py
airbyte_cdk/exception_handler.py
airbyte_cdk/legacy/__init__.py
airbyte_cdk/legacy/sources/__init__.py
airbyte_cdk/legacy/sources/declarative/__init__.py
airbyte_cdk/legacy/sources/declarative/declarative_source.py
airbyte_cdk/legacy/sources/declarative/declarative_stream.py
airbyte_cdk-7.7.1.dist-info/LICENSE.txt
airbyte_cdk-7.7.1.dist-info/LICENSE_SHORT
airbyte_cdk-7.7.1.dist-info/METADATA
airbyte_cdk-7.7.1.dist-info/WHEEL
airbyte_cdk-7.7.1.dist-info/entry_points.txt
airbyte_cdk-7.7.1.dist-info/RECORD
