Metadata-Version: 2.1
Name: airbyte-cdk
Version: 7.7.1
Summary: A framework for writing Airbyte Connectors.
Home-page: https://airbyte.com
License: MIT
Keywords: airbyte,connector-development-kit,cdk
Author: Airbyte
Author-email: contact@airbyte.io
Requires-Python: >=3.10,<3.14
Classifier: Development Status :: 3 - Alpha
Classifier: Intended Audience :: Developers
Classifier: License :: OSI Approved :: MIT License
Classifier: Programming Language :: Python :: 3
Classifier: Programming Language :: Python :: 3.10
Classifier: Programming Language :: Python :: 3.11
Classifier: Programming Language :: Python :: 3.12
Classifier: Programming Language :: Python :: 3.13
Classifier: Topic :: Scientific/Engineering
Classifier: Topic :: Software Development :: Libraries :: Python Modules
Provides-Extra: dev
Provides-Extra: file-based
Provides-Extra: manifest-server
Provides-Extra: sql
Provides-Extra: vector-db-based
Requires-Dist: Jinja2 (>=3.1.2,<3.2.0)
Requires-Dist: PyYAML (>=6.0.1,<7.0.0)
Requires-Dist: airbyte-protocol-models-dataclasses (>=0.17.1,<0.18.0)
Requires-Dist: anyascii (>=0.3.2,<0.4.0)
Requires-Dist: avro (>=1.11.2,<1.13.0) ; extra == "file-based"
Requires-Dist: backoff
Requires-Dist: boltons (>=25.0.0,<26.0.0)
Requires-Dist: cachetools
Requires-Dist: click (>=8.1.8,<9.0.0)
Requires-Dist: cohere (>=4.21,<6.0.0) ; extra == "vector-db-based"
Requires-Dist: cryptography (>=44.0.0,<45.0.0)
Requires-Dist: dateparser (>=1.2.2,<2.0.0)
Requires-Dist: ddtrace (>=3,<4) ; extra == "manifest-server"
Requires-Dist: dpath (>=2.1.6,<3.0.0)
Requires-Dist: dunamai (>=1.22.0,<2.0.0)
Requires-Dist: fastapi (>=0.116.1) ; extra == "manifest-server"
Requires-Dist: fastavro (>=1.11.0,<2.0.0) ; extra == "file-based"
Requires-Dist: genson (==1.3.0)
Requires-Dist: google-cloud-secret-manager (>=2.17.0,<3.0.0)
Requires-Dist: isodate (>=0.6.1,<0.7.0)
Requires-Dist: jsonref (>=1,<2)
Requires-Dist: jsonschema (>=4.17.3,<5.0)
Requires-Dist: langchain_community (>=0.4,<0.5) ; extra == "vector-db-based"
Requires-Dist: langchain_core (>=1.2.5,<2.0.0) ; extra == "vector-db-based"
Requires-Dist: langchain_text_splitters (>=1.0.0,<2.0.0) ; extra == "vector-db-based"
Requires-Dist: markdown ; extra == "file-based"
Requires-Dist: nltk (==3.9.1)
Requires-Dist: openai[embeddings] (==0.27.9) ; extra == "vector-db-based"
Requires-Dist: openpyxl (>=3.1.0,<4.0.0) ; extra == "file-based"
Requires-Dist: orjson (>=3.10.7,<4.0.0)
Requires-Dist: packaging
Requires-Dist: pandas (==2.2.3)
Requires-Dist: pdf2image (==1.16.3) ; extra == "file-based"
Requires-Dist: pdfminer.six (==20221105) ; extra == "file-based"
Requires-Dist: pyarrow (>=19.0.0,<20.0.0) ; extra == "file-based"
Requires-Dist: pydantic (>=2.7,<3.0)
Requires-Dist: pyjwt (>=2.8.0,<3.0.0)
Requires-Dist: pyrate-limiter (>=3.1.0,<3.2.0)
Requires-Dist: pytesseract (==0.3.10) ; extra == "file-based"
Requires-Dist: pytest (>=7,<8) ; extra == "dev"
Requires-Dist: python-calamine (==0.2.3) ; extra == "file-based"
Requires-Dist: python-dateutil (>=2.9.0,<3.0.0)
Requires-Dist: python-snappy (==0.7.3) ; extra == "file-based"
Requires-Dist: python-ulid (>=3.0.0,<4.0.0)
Requires-Dist: pytz (==2024.2)
Requires-Dist: rapidfuzz (>=3.10.1,<4.0.0)
Requires-Dist: referencing (>=0.36.2)
Requires-Dist: requests
Requires-Dist: requests_cache
Requires-Dist: rich
Requires-Dist: rich-click (>=1.8.8,<2.0.0)
Requires-Dist: serpyco-rs (>=1.10.2,<2.0.0)
Requires-Dist: setuptools (>=80.9.0,<81.0.0)
Requires-Dist: sqlalchemy (>=2.0,<3.0,!=2.0.36) ; extra == "sql"
Requires-Dist: tiktoken (==0.8.0) ; extra == "vector-db-based"
Requires-Dist: typing-extensions
Requires-Dist: unidecode (>=1.3.8,<2.0.0)
Requires-Dist: unstructured.pytesseract (>=0.3.12) ; extra == "file-based"
Requires-Dist: unstructured[docx,pptx] (==0.10.27) ; extra == "file-based"
Requires-Dist: uvicorn (>=0.35.0) ; extra == "manifest-server"
Requires-Dist: wcmatch (==10.0)
Requires-Dist: whenever (>=0.7.3,<0.9.0)
Requires-Dist: xmltodict (>=0.13,<0.15)
Project-URL: Documentation, https://docs.airbyte.io/
Project-URL: Repository, https://github.com/airbytehq/airbyte-python-cdk
